odoo/addons/partner_multi_company/README.rst
odoo/addons/partner_multi_company/__init__.py
odoo/addons/partner_multi_company/__manifest__.py
odoo/addons/partner_multi_company/hooks.py
odoo/addons/partner_multi_company/i18n/de.po
odoo/addons/partner_multi_company/i18n/es.po
odoo/addons/partner_multi_company/i18n/fr.po
odoo/addons/partner_multi_company/i18n/hr.po
odoo/addons/partner_multi_company/i18n/it.po
odoo/addons/partner_multi_company/i18n/partner_multi_company.pot
odoo/addons/partner_multi_company/i18n/pt.po
odoo/addons/partner_multi_company/i18n/tr.po
odoo/addons/partner_multi_company/models/__init__.py
odoo/addons/partner_multi_company/models/res_company.py
odoo/addons/partner_multi_company/models/res_partner.py
odoo/addons/partner_multi_company/models/res_users.py
odoo/addons/partner_multi_company/readme/CONTRIBUTORS.md
odoo/addons/partner_multi_company/readme/DESCRIPTION.md
odoo/addons/partner_multi_company/readme/INSTALL.md
odoo/addons/partner_multi_company/readme/ROADMAP.md
odoo/addons/partner_multi_company/readme/USAGE.md
odoo/addons/partner_multi_company/static/description/icon.png
odoo/addons/partner_multi_company/static/description/index.html
odoo/addons/partner_multi_company/tests/__init__.py
odoo/addons/partner_multi_company/tests/test_partner_multi_company.py
odoo/addons/partner_multi_company/views/res_partner_view.xml
odoo_addon_partner_multi_company-18.0.1.0.1.2.dist-info/METADATA
odoo_addon_partner_multi_company-18.0.1.0.1.2.dist-info/WHEEL
odoo_addon_partner_multi_company-18.0.1.0.1.2.dist-info/top_level.txt
odoo_addon_partner_multi_company-18.0.1.0.1.2.dist-info/RECORD
